CHANGES.md
messages/.coverage
messages/__init__.py
messages/_exceptions.py
messages/_interface.py
messages/_utils.py
messages/email_.py
messages/slack.py
messages/telegram.py
messages/text.py
messages/whatsapp.py
messages-0.7.1.dist-info/LICENSE
messages-0.7.1.dist-info/WHEEL
messages-0.7.1.dist-info/METADATA
messages-0.7.1.dist-info/RECORD
